{
  "id": 131445704,
  "key": "n47041a47f048",
  "title": "Lotus Sutra 16｜Eternal Tathāgata",
  "url": "https://note.com/flow_theory/n/n47041a47f048",
  "published_at": "2025-10-26T10:01:33+09:00",
  "like_count": 3,
  "body_text": "【ホーリーイーグルマウンテン上空：虚空会議室】\n\n地上から数千メートル上空。\n物理法則を無視して浮かぶ、透明な床の空間。\n足元のガラス越しに、ホーリーイーグルマウンテンの頂が遥か下に小さく見える。\n\nここは「虚空会議室」と呼ばれる、悟りを開いた者だけが召集される特別な空間だった。\n四方八方、どこまでも続く空。壁も天井もない。\nただ、円形のテーブルと椅子だけが、虚空に浮かんでいる。\n\nセゾンはテーブルの中央に立ち、周囲に座るクルーたちを見渡した。\nシャリア、マイトレーヤ、マンジュシュリー、カッサパ...名だたる猛者たちが、緊張の面持ちで座っている。\n\n「なぁ、お前たち。聞いてくれ。」\nセゾンの声が虚空に響く。\n「今から言うことは、今までの全てをひっくり返す爆弾発言だ。心して聞いてくれ。」\n\nセゾンのクルーたちは息を呑んだ。マイトレーヤが代表して尋ねる。\n「セゾン、それは一体...？」\n\nセゾンは苦笑いを浮かべた。\n「お前らさぁ、オレのこと、どう思ってる？」\n\n「それは...29歳で出家して、35歳で悟りを開いた、偉大なるブッダです。」\n\n「はっ！」\nセゾンは声を上げて笑った。その笑い声が虚空を震わせる。\n\n「違うね。大間違いだ。」\n\n全員が凍りついた。誰もセゾンが何を言っているのか理解できない。\n\n「いいか、よく聞け。オレが本当に悟りを開いたのはな...」\n\nセゾンは一呼吸置いた。次の言葉が、永遠に彼らの世界観を変えることになる。\n\n「五百億塵点劫っていう、お前らの頭脳では理解不能なほどの過去の話だ。」\n\n「は...？」\n\n「説明してやる。まず五百億の世界を粉々に砕け。その粉を全部集めろ。\nそして、千の世界を通るごとに一粒ずつ落としていけ。\n全部落とし終わったら、今度は粉を落とした世界も落とさなかった世界も、全部まとめてまた粉々に砕け。」\n\nクルーたちの顔が青ざめていく。\n\n「その粉の数だけ『劫』っていう、このクソ長い時間単位を掛け算してみろ。\nそれより更に昔に、オレはもう悟ってたんだよ。」\n\nマイトレーヤの膝が震え始めた。\n「じゃあ...じゃあ、今まで私たちが見てきたセゾンは...」\n\n「こんなものは見せかけの衣装だ。コスプレだよ、コスプレ。」\n\nセゾンはあっけらかんと言い放った。\n\n「あんなものは全部お芝居だよ。『プリンスとして生まれました〜』『苦行しました〜』『菩提樹の下で悟りました〜』...全部演技だ。お前らのレベルに合わせた、壮大な学芸会だよ。」\n\n虚空が揺れた。いや、揺れているのは仲間たちの心だった。\n\n「セ..セゾン！なんで...なんでそんなことを...！！！」\nクルーたちの間で最も厳格なカッサパは語気に怒りを込めた\n\n「決まってんだろ。」\nセゾンの表情が真剣になる。\n「お前らが、あまりにも依存体質だからだよ。」\n\n痛烈な一言が、虚空に突き刺さる。\n\n「オレがいつもそばにいるって知ったら、お前らどうする？努力しねぇだろ。\n挙句の果ては『ほっときやセゾンがなんとかするだろ』って甘えるだろうがよぉ!!」\n\n返す言葉がなかった。誰も反論できなかった。\n\n「だからオレは死んだフリをする。『ああ、セゾンが死んじまった！もう頼れない！自分でなんとかしなきゃ！』ってな。そうやって、お前らを自立させるんだ。」\n\nセゾンは宙に浮かびながら、腕を組んだ。\n\n「大昔の例え話の『良医治子』って言うやつだ。名医の親父が、毒を飲んで苦しむガキどもに薬を残して、死んだフリして旅に出る。『親父が死んだ！』ってショックで正気に戻ったガキどもは、ようやく薬を飲む。そしたら親父が『サプラ〜イズ！じつは生きてました〜』って帰ってくる。」\n\n「そ、そんなの...詐欺じゃ...」\n普段は冷静で知的なマンジュシュリーが、動揺を隠せず震えながら言った。\n\n「方便だよ、方便。愛のムチってやつ。」\n\nセゾンの背後に、今度は無数の光の粒子が現れ始めた。それは星々のように輝き、宇宙そのものを形成していく。\n\n「オレはな、このクソつまらない無限の時間、ずーっとお前らを見守ってきた。姿を変え、名前を変え、時には敵役にもなって、お前らを導いてきたんだ。」\n\n光の粒子が次第に形を成していく。そこには無数のセゾンの姿があった。王として、乞食として、商人として、時には獣として。\n\n「毎日毎日、オレは考えてる。『どうやったらこいつらが自分の足で立てるようになるかな』ってな。」\n\nマイトレーヤは涙を流していた。理解を超えた慈悲の深さに、心が震えていた。\n\n「セゾン...オレたちは...」\n\n「分かったら、もうオレに泣きつくな。お前らの中にも、オレと同じポテンシャルがあるんだ。オレはそれを引き出すために、この壮大な学芸会をやってんだ。」\n\n虚空に浮かぶクルーたちは、それぞれ複雑な表情を浮かべていた。安堵、恐れ、感動、そして...ある種の寂しさ。\n\n「でもな、一つだけ本当のことがある。」\n\nセゾンの声が、急に優しくなった。\n\n「お前らをブッダにしたいっていう、この想いだけは、永遠に変わらない。それだけは、演技じゃない。」\n\nその瞬間、虚空全体が黄金の光に包まれた。\n\nクルーたちは理解した。この永遠の存在は、無限の時を超えて、ただひたすらに彼らの幸せを願い続けているのだと。\n\nそして同時に、恐ろしい真実も理解した。\nもう、甘えることは許されない。\n自分自身が、ブッダになるしかないのだと。\n\n「さぁ、真実を知っちまったからには、覚悟決めろよ。オレはいつか必ず『死ぬフリ』をする。その時、お前らはどうする？」\n\nセゾンは、挑戦的な笑みを浮かべた。\n\n「泣き喚いて終わるか？それとも、自分が次のブッダになるか？」\n\n選択は、彼らに委ねられた。\n永遠の命を持つ教師は、永遠に生徒たちの成長を待ち続ける。\nそれが、本当の慈悲なのだから。\n\n　〜 法華経｜如来寿量品第十六より\n\n## 登場人物\n\nセゾン（世尊 / Bhagavān）\n\n別名：釈迦牟尼仏（Śākyamuni Buddha）、タターガタ（如来 / Tathāgata）\n\nシャーキャ族の王子として生まれ、29歳で出家、35歳で悟りを開いた...と誰もが信じているブッダ。しかし実際は、無限の過去から悟りを開いていたタターガタ(永遠の存在)。方便、神通力、そして圧倒的なカリスマでクルーたちを導く。\n\nシャリア（舎利弗 / Śāriputra）\n\n智慧第一：セゾンのバディであり親友でもある右腕的存在。冷静沈着で頭脳明晰だが、セゾンの真の力の前では理解が追いつかない。セゾンにはいつも馬鹿にされているがそれが愛情からの照れ隠しであることを理解している。算数の成績は世尊より良い。\n\nマイトレーヤ（弥勒菩薩 / Maitreya）\n\n未来仏：慈悲深く穏やかな性格。如来寿量品ではクルーの代表として質問する役割。\n\nマンジュシュリー（文殊菩薩 / Mañjuśrī）\n\n智慧の菩薩:冷静で知的。哲学的な議論を好む。\n\nカッサパ（摩訶迦葉 / Mahākāśyapa）\n\n頭陀第一：厳格で規律を重んじる。セゾンが死んだフリしてる間はリーダー役を担う。\n\n関連記事\n分別功徳品第十七をノベライズ\n\n目次\n\n登場人物\n\n仏教の本質から考える本当の「救い」とは"
}