{
  "id": 135172665,
  "key": "n8ae1b0faf3fd",
  "title": "SPACE対談アーカイブ",
  "url": "https://note.com/flow_theory/n/n8ae1b0faf3fd",
  "published_at": "2025-11-22T09:57:50+09:00",
  "like_count": 2,
  "tags": "対談, アーカイブ, FLOW, space",
  "body_text": "## 12/18 対談 : 牧口常三郎の目指した価値創造はどこへ向かうのか\n\n## 12/11 対談 : 教育者としての牧口常三郎 第三部\n\n## 12/4 対談 : 教育者としての牧口常三郎 第二部\n\n## 11/27 対談 : 教育者としての牧口常三郎\n\n11/21 つとみんさん「つとみんラジオ」\n\nhttps://t.co/hlvHISWKSZ\n— つとみんの桜梅桃李ルーム.season2🌈🌸 (@1vNXt1pUH7UwJoF) November 21, 2025\n\n11/11 師恩さんとの対談\n\nhttps://t.co/L4xIo1Jq2Y\n— 師恩〜shion〜RICE (@shion20060907) November 11, 2025\n\n続き\n\nhttps://t.co/CqmWx9616n\n— 師恩〜shion〜RICE (@shion20060907) November 11, 2025\n\nハイライト\n  \n## FLOWってこんな奴"
}